anomed_deanonymizer/__init__.py
anomed_deanonymizer/deanonymizer.py
anomed_deanonymizer/deanonymizer_server.py
anomed_deanonymizer-0.0.11.dist-info/METADATA
anomed_deanonymizer-0.0.11.dist-info/WHEEL
anomed_deanonymizer-0.0.11.dist-info/licenses/LICENSE
anomed_deanonymizer-0.0.11.dist-info/RECORD
